<?xml version="1.0" encoding="UTF-8"?><record_update table="sys_app">
    <sys_app action="INSERT_OR_UPDATE">
        <active>true</active>
        <can_edit_in_studio>false</can_edit_in_studio>
        <enforce_license>none</enforce_license>
        <js_level>helsinki_es5</js_level>
        <licensable>true</licensable>
        <license_category>none</license_category>
        <license_model>none</license_model>
        <logo/>
        <menu display_value="NSOne Integration">39623600dbff330051bde4da4b961986</menu>
        <name>NSOne Integration</name>
        <private>false</private>
        <restrict_table_access>false</restrict_table_access>
        <runtime_access_tracking>permissive</runtime_access_tracking>
        <scope>x_401282_nsone_int</scope>
        <scoped_administration>false</scoped_administration>
        <short_description/>
        <source>x_401282_nsone_int</source>
        <store_correlation_id/>
        <store_url/>
        <sys_class_name>sys_app</sys_class_name>
        <sys_code/>
        <sys_created_by>admin</sys_created_by>
        <sys_created_on>2019-09-05 13:42:13</sys_created_on>
        <sys_id>79627e08dbbf330051bde4da4b961982</sys_id>
        <sys_mod_count>1</sys_mod_count>
        <sys_updated_by>admin</sys_updated_by>
        <sys_updated_on>2019-09-09 18:42:47</sys_updated_on>
        <template/>
        <trackable>true</trackable>
        <user_role display_value="x_401282_nsone_int.user" name="x_401282_nsone_int.user">75623600dbff330051bde4da4b961989</user_role>
        <vendor/>
        <vendor_prefix/>
        <version>1.0.1</version>
    </sys_app>
</record_update>
